constellate/__init__.py
constellate/__version__.py
constellate/py.typed
constellate/cli/__init__.py
constellate/cli/argument/__init__.py
constellate/cli/argument/unparse.py
constellate/compression/__init__.py
constellate/compression/zip/__init__.py
constellate/compression/zip/zip.py
constellate/compression/zstd/__init__.py
constellate/compression/zstd/common.py
constellate/compression/zstd/pyzstd.py
constellate/compression/zstd/zstandard.py
constellate/concurrency/__init__.py
constellate/concurrency/asyncio/__init__.py
constellate/concurrency/asyncio/tasks.py
constellate/concurrency/pebble/__init__.py
constellate/concurrency/pebble/pool_cleanup.py
constellate/concurrency/simple/__init__.py
constellate/concurrency/simple/simple.py
constellate/concurrency/std/__init__.py
constellate/concurrency/std/pool.py
constellate/constant/__init__.py
constellate/constant/concurrency.py
constellate/constant/debug.py
constellate/constant/platform.py
constellate/container/__init__.py
constellate/container/orchestration/__init__.py
constellate/container/orchestration/k8s/__init__.py
constellate/container/orchestration/k8s/probe.py
constellate/cryptography/__init__.py
constellate/cryptography/digest/__init__.py
constellate/cryptography/digest/hexadecimal.py
constellate/database/__init__.py
constellate/database/common/__init__.py
constellate/database/common/databasetype.py
constellate/database/migration/__init__.py
constellate/database/migration/constant.py
constellate/database/migration/metadata.py
constellate/database/migration/migrate.py
constellate/database/migration/migrationcontext.py
constellate/database/migration/migrationstep.py
constellate/database/migration/tablecontext.py
constellate/database/migration/standard/__init__.py
constellate/database/migration/standard/base.py
constellate/database/migration/standard/migrate.py
constellate/database/migration/standard/table.py
constellate/database/sparql/__init__.py
constellate/database/sparql/query.py
constellate-0.8.24.dist-info/licenses/LICENSE
constellate-0.8.24.dist-info/METADATA
constellate-0.8.24.dist-info/WHEEL
constellate-0.8.24.dist-info/top_level.txt
constellate-0.8.24.dist-info/RECORD
