Metadata-Version: 2.4
Name: constellate
Version: 0.8.24
Summary: A bunch of utilities aggregated over time
Author-email: David Andreoletti <none@provided.yet>
License-Expression: LicenseRef-Proprietary
Project-URL: repository, https://github.com/davidandreoletti/constellate
Keywords: constellate
Classifier: Development Status :: 4 - Beta
Classifier: Intended Audience :: Developers
Classifier: Natural Language :: English
Classifier: Operating System :: MacOS :: MacOS X
Classifier: Operating System :: POSIX :: Linux
Classifier: Programming Language :: Python
Classifier: Programming Language :: Python :: 3
Classifier: Programming Language :: Python :: 3.10
Classifier: Programming Language :: Python :: 3.11
Classifier: Programming Language :: Python :: 3.12
Classifier: Programming Language :: Python :: 3.13
Classifier: Programming Language :: Python :: 3.14
Requires-Python: <3.15,>=3.10
License-File: LICENSE
Requires-Dist: decorator>=5.1.0
Requires-Dist: aioitertools>=0.8.0
Requires-Dist: psutil>=5.7.0
Requires-Dist: pendulum>=3.0.0
Requires-Dist: requests>=2.25.0
Requires-Dist: memory-tempfile>=2.2.3
Requires-Dist: bidict>=0.21.4
Requires-Dist: attrs>=20.3.0
Requires-Dist: jsonmerge>=1.8.0
Requires-Dist: jsonschema>=4.7.2
Requires-Dist: Deprecated>=1.2.12
Requires-Dist: importlib-resources>=5.1.4
Requires-Dist: typing-extensions>=4.3.0
Requires-Dist: tqdm>=4.62.3
Requires-Dist: regex>=2021.11.10
Requires-Dist: blake3>=0.3.1
Requires-Dist: sqlparse>=0.4.2
Requires-Dist: stackeddag>=0.3.3
Provides-Extra: cliargs
Requires-Dist: argunparse>=0.2.0; python_version >= "3.11" and extra == "cliargs"
Provides-Extra: sqlalchemy
Requires-Dist: SQLAlchemy<=2.0.43; extra == "sqlalchemy"
Requires-Dist: sqlalchemy-utils>=0.37.9; extra == "sqlalchemy"
Requires-Dist: sqlalchemy-json>=0.4.0; extra == "sqlalchemy"
Requires-Dist: sqlalchemy_mixins>=2.0; extra == "sqlalchemy"
Requires-Dist: aiosqlite>=0.21.0; extra == "sqlalchemy"
Requires-Dist: asyncpg>=0.30.0; extra == "sqlalchemy"
Requires-Dist: networkx>=2.8.5; extra == "sqlalchemy"
Provides-Extra: pandas
Requires-Dist: pandas>=2.0.0; extra == "pandas"
Requires-Dist: pandas-log>=0.1.7; extra == "pandas"
Requires-Dist: pandera!=0.13.4,>=0.20.1; extra == "pandas"
Requires-Dist: hypothesis>=6.54.4; extra == "pandas"
Provides-Extra: numpy
Requires-Dist: numpy>=1.21.4; extra == "numpy"
Provides-Extra: numba
Requires-Dist: numba-progress>=0.0.3; extra == "numba"
Provides-Extra: sparql
Requires-Dist: rdflib>=6.3.0; extra == "sparql"
Requires-Dist: SPARQL-Burger>=1.0.2; extra == "sparql"
Provides-Extra: zstd
Requires-Dist: pyzstd>=0.15.10; extra == "zstd"
Provides-Extra: logging
Requires-Dist: narration>=0.2.20; extra == "logging"
Requires-Dist: colorlog>=6.8.2; extra == "logging"
Provides-Extra: concurrencypebble
Requires-Dist: Pebble>=4.6.3; extra == "concurrencypebble"
Provides-Extra: timeinterval
Requires-Dist: portion>=2.2.0; extra == "timeinterval"
Provides-Extra: stackframesampler
Requires-Dist: austin-tui>=1.2.3; extra == "stackframesampler"
Requires-Dist: austin-dist>=3.6.0; extra == "stackframesampler"
Provides-Extra: debuggevscode
Requires-Dist: debugpy>=1.8.2; extra == "debuggevscode"
Provides-Extra: debuggerpycharm
Requires-Dist: pydevd-pycharm>=231.0.0; sys_platform == "linux" and extra == "debuggerpycharm"
Provides-Extra: all
Requires-Dist: constellate[cliargs,concurrencypebble,logging,numba,numpy,pandas,sparql,sqlalchemy,timeinterval,zstd]; extra == "all"
Dynamic: license-file
